README.txt
setup.cfg
setup.py
docs/HISTORY.txt
docs/INSTALL.txt
docs/LICENSE.GPL
docs/LICENSE.txt
quills/__init__.py
quills.remoteblogging.egg-info/PKG-INFO
quills.remoteblogging.egg-info/SOURCES.txt
quills.remoteblogging.egg-info/dependency_links.txt
quills.remoteblogging.egg-info/entry_points.txt
quills.remoteblogging.egg-info/namespace_packages.txt
quills.remoteblogging.egg-info/not-zip-safe
quills.remoteblogging.egg-info/requires.txt
quills.remoteblogging.egg-info/top_level.txt
quills/remoteblogging/__init__.py
quills/remoteblogging/configure.zcml
quills/remoteblogging/interfaces.py
quills/remoteblogging/utils.py
quills/remoteblogging/browser/__init__.py
quills/remoteblogging/browser/metaweblogapi.py
quills/remoteblogging/tests/__init__.py
quills/remoteblogging/tests/fixedBugs.txt
quills/remoteblogging/tests/metaweblogapi.txt
quills/remoteblogging/tests/quills_powered.gif
quills/remoteblogging/tests/test_caselessdict.py
quills/remoteblogging/tests/test_doctests.py