Metadata-Version: 1.0
Name: quills.remoteblogging
Version: 1.7.0c1
Summary: Interfaces and implementation of remote blogging for Zope3/Plone.
Home-page: http://svn.plone.org/svn/collective/quills.remoteblogging/
Author: Tim Hicks
Author-email: tim@sitefusion.co.uk
License: GPL
Keywords: Weblog
Platform: UNKNOWN
Classifier: Framework :: Plone
Classifier: Framework :: Zope2
Classifier: Framework :: Zope3
Classifier: Programming Language :: Python
Classifier: Topic :: Software Development :: Libraries :: Python Modules
